README.md
setup.py
HystrixBox/Parsers.py
HystrixBox/__init__.py
HystrixBox/evaluator.py
HystrixBox/keys.py
HystrixBox/menu.py
HystrixBox/modules_parser.py
HystrixBox/personal_parser.py
HystrixBox/Decoders/ASCIICipher.py
HystrixBox/Decoders/Base64Cipher.py
HystrixBox/Decoders/CaesarCipher.py
HystrixBox/Decoders/Decoder.py
HystrixBox/Decoders/HashCipher.py
HystrixBox/Decoders/ReverseCipher.py
HystrixBox/Decoders/T9Chipher.py
HystrixBox/Decoders/__init__.py
HystrixBox/Evaluators/Evaluator.py
HystrixBox/Evaluators/__init__.py
HystrixBox/Evaluators/flag_check.py
HystrixBox/Evaluators/letter_check.py
HystrixBox/Evaluators/word_check.py
HystrixBox/Extractors/Extractor.py
HystrixBox/Extractors/__init__.py
HystrixBox/Extractors/emailExtractor.py
HystrixBox/Extractors/ipExtractor.py
HystrixBox/Extractors/md5Extractor.py
HystrixBox/Extractors/urlExtractor.py
HystrixBox/Tools/__init__.py
HystrixBox/Tools/emailAnalyzer.py
HystrixBox/Tools/hideInImage.py
HystrixBox/Tools/recursiveDecompression.py
HystrixBox/Tools/strings.py
HystrixBox/Tools/fileType/__init__.py
HystrixBox/Tools/fileType/applications.py
HystrixBox/Tools/fileType/archives.py
HystrixBox/Tools/fileType/audio.py
HystrixBox/Tools/fileType/extenstion.py
HystrixBox/Tools/fileType/extenstionDB.py
HystrixBox/Tools/fileType/font.py
HystrixBox/Tools/fileType/getFileExtenstion.py
HystrixBox/Tools/fileType/images.py
HystrixBox/Tools/fileType/video.py
HystrixBox/Utils/__init__.py
HystrixBox/Utils/searchFlag.py
Hystrix_Box.egg-info/PKG-INFO
Hystrix_Box.egg-info/SOURCES.txt
Hystrix_Box.egg-info/dependency_links.txt
Hystrix_Box.egg-info/entry_points.txt
Hystrix_Box.egg-info/requires.txt
Hystrix_Box.egg-info/top_level.txt
tests/__init__.py
tests/test_ASCIICipher.py
tests/test_Base64Cipher.py
tests/test_CaesarCipher.py
tests/test_HashCipher.py
tests/test_ReverseCipher.py
tests/test_T9Chipher.py
tests/test_emailAnalyzer.py
tests/test_emailExtractor.py
tests/test_getFileExtenstion.py
tests/test_hideInImage.py
tests/test_ipExtractor.py
tests/test_md5Extractor.py
tests/test_modules_parser.py
tests/test_recursiveDecompression.py
tests/test_searchFlag.py
tests/test_strings.py
tests/test_urlExtractor.py