Metadata-Version: 2.1
Name: Hystrix-Box
Version: 0.2
Summary: Ultimate toolbox for solving CTF challenges
Home-page: https://github.com/zomry1/Hystrix-Box/
Author: zomry1
Author-email: zomry1@gmail.com
License: MIT
Download-URL: https://github.com/zomry1/Hystrix-Box/archive/v0.1-alpha.tar.gz
Keywords: CTF,toolbox,challenges
Platform: UNKNOWN
Classifier: Development Status :: 3 - Alpha
Classifier: Intended Audience :: Developers
Classifier: Topic :: Software Development :: Build Tools
Classifier: License :: OSI Approved :: MIT License
Classifier: Programming Language :: Python :: 3.6
